bashlist/__init__.py
bashlist/__main__.py
bashlist/bashlist.py
bashlist/cli.py
bashlist/config.py
bashlist/database.py
bashlist-0.1.4.dist-info/entry_points.txt
bashlist-0.1.4.dist-info/LICENSE
bashlist-0.1.4.dist-info/WHEEL
bashlist-0.1.4.dist-info/METADATA
bashlist-0.1.4.dist-info/RECORD
