Metadata-Version: 2.1
Name: bashlist
Version: 0.1.4
Summary: Packages for bashlist
Author-email: Oluwaseun <tanimolaoluwaseun70@gmail.com>
Classifier: License :: OSI Approved :: MIT License
Project-URL: Home, https://github.com/Oluwaseun241/bashlist_cli
